heppdap/__init__.py
heppdap/allevents.py
heppdap/channelnames.py
heppdap/event_classes.py
heppdap/fnameparser.py
heppdap/main.py
heppdap/read_data.py
heppdap/spectrums.py
heppdap/stats.py
heppdap/test.py
scripts/__init__.py
scripts/event_classes.py
scripts/main.py
scripts/read_data.py
scripts/stats.py
heppdap-2.0.0.dist-info/METADATA
heppdap-2.0.0.dist-info/WHEEL
heppdap-2.0.0.dist-info/entry_points.txt
heppdap-2.0.0.dist-info/top_level.txt
heppdap-2.0.0.dist-info/RECORD
