Metadata-Version: 2.1
Name: heppdap
Version: 2.0.0
Summary: High Energy Particle Physics Data Analysis Package
Home-page: https://github.com/bweindorf/HEPPDAP.git
Author: Brandon Weindorf
Author-email: bjweindorf@gmail.com
License: UNKNOWN
Platform: UNKNOWN
Classifier: Programming Language :: Python :: 3
Classifier: License :: OSI Approved :: MIT License
Classifier: Operating System :: OS Independent
Requires-Python: >=3.6
Requires-Dist: matplotlib
Requires-Dist: scipy
Requires-Dist: numpy
Requires-Dist: pandas
Requires-Dist: wxPython
